pyreflect/__init__.py
pyreflect/__main__.py
pyreflect/cli/__init__.py
pyreflect/cli/init_content.py
pyreflect/cli/initialize.py
pyreflect/cli/main.py
pyreflect/config/__init__.py
pyreflect/config/errors.py
pyreflect/config/load_config.py
pyreflect/config/runtime.py
pyreflect/input/__init__.py
pyreflect/input/data_processor.py
pyreflect/input/reflectivity_data_generator.py
pyreflect/models/__init__.py
pyreflect/models/autoencoder.py
pyreflect/models/chi_pred_model_trainer.py
pyreflect/models/cnn.py
pyreflect/models/config.py
pyreflect/models/mlp.py
pyreflect/models/model_trainer.py
pyreflect/models/nr_sld_model_trainer.py
pyreflect/pipelines/__init__.py
pyreflect/pipelines/helper.py
pyreflect/pipelines/inference.py
pyreflect/pipelines/reflectivity_pipeline.py
pyreflect/pipelines/run_chi_prediction.py
pyreflect/pipelines/run_sld_prediction.py
pyreflect/pipelines/sld_profile_pred_chi.py
pyreflect/pipelines/train_autoencoder_mlp_chi_pred.py
pyreflect/tests/__init__.py
pyreflect/tests/test1.py
pyreflect_nr-1.4.1.dist-info/METADATA
pyreflect_nr-1.4.1.dist-info/WHEEL
pyreflect_nr-1.4.1.dist-info/licenses/LICENSE
pyreflect_nr-1.4.1.dist-info/RECORD
