Metadata-Version: 2.4
Name: pyreflect-nr
Version: 1.4.1
Summary: The package tool for neutron reflectivity analysis
License-Expression: MIT
License-File: LICENSE
Author: Yuqing Qiao
Author-email: qiao.yuqi@northeastern.edu
Requires-Python: >=3.10
Classifier: Programming Language :: Python :: 3
Classifier: Operating System :: OS Independent
Requires-Dist: allpairspy (>=2.5.1,<3.0.0)
Requires-Dist: llvmlite (>=0.44.0)
Requires-Dist: numba (>=0.61.0)
Requires-Dist: numpy (==2.1.0)
Requires-Dist: opencv-python (>=4.11.0.86,<5.0.0.0)
Requires-Dist: pandas (>=2.2.3,<3.0.0)
Requires-Dist: pyyaml (>=6.0.2,<7.0.0)
Requires-Dist: refl1d (>=1.0.0a0,<2.0.0)
Requires-Dist: refnx
Requires-Dist: scikit-learn (>=1.6.1,<2.0.0)
Requires-Dist: scipy (>=1.15.1,<2.0.0)
Requires-Dist: seaborn (>=0.13.2,<0.14.0)
Requires-Dist: torch (==2.5.1)
Requires-Dist: tqdm (>=4.67.1,<5.0.0)
Requires-Dist: typer (>=0.15.1,<0.16.0)
Project-URL: Homepage, https://github.com/williamQyq/pyreflect
Project-URL: Issues, https://github.com/williamQyq/pyreflect/issues
